<?xml version="1.0" encoding="utf-8"?>
<tm id="@ParkBrkLatchPos$I">
	<tu xmlns:lang="eng">Parking brake latching position.</tu>
	<tu xmlns:lang="nld">Vergrendelstand van handrem.</tu>
	<tu xmlns:lang="fra">Position de verrouillage du frein de stationnement.</tu>
	<tu xmlns:lang="deu">Handbremsen-Raststellung.</tu>
	<tu xmlns:lang="ita">Posizione bloccaggio freno di stazionamento.</tu>
	<tu xmlns:lang="jpn">パーキング ブレーキ ラッチング ポジション</tu>
	<tu xmlns:lang="ptg">Posição de engate do travão de mão.</tu>
	<tu xmlns:lang="ptb">Posição da trava do freio de estacionamento.</tu>
	<tu xmlns:lang="rus">Положение фиксации стояночного тормоза.</tu>
	<tu xmlns:lang="esp">Posición de enganche del freno de estacionamiento.</tu>
	<tu xmlns:lang="chs">驻车制动器锁闭位置。</tu>
	<tu xmlns:lang="kor">주차 브레이크 잠금 위치</tu>
</tm>