<?xml version="1.0" encoding="utf-8"?>
<tm id="@phillipss_1086106773$X">
	<tu xmlns:lang="eng">Optional fitment</tu>
	<tu xmlns:lang="nld">Optionele installatie.</tu>
	<tu xmlns:lang="fra">Montage facultatif.</tu>
	<tu xmlns:lang="deu">Wahlweise Ausstattung</tu>
	<tu xmlns:lang="ita">Montaggio facoltativo</tu>
	<tu xmlns:lang="jpn">オプション装備</tu>
	<tu xmlns:lang="ptg">Montagem opcional</tu>
	<tu xmlns:lang="ptb">Instalação opcional</tu>
	<tu xmlns:lang="rus">Дополнительное оборудование</tu>
	<tu xmlns:lang="esp">Montaje en opción</tu>
	<tu xmlns:lang="chs">可选装备</tu>
	<tu xmlns:lang="kor">선택적 장착</tu>
</tm>