<?xml version="1.0" encoding="utf-8" ?>
<tm id="@PCMD_SEC_BOOST_VALVE">
	<tu xmlns:lang="eng">Turbine shut-off valve</tu>
	<tu xmlns:lang="nld">Uitschakelklep turbine</tu>
	<tu xmlns:lang="fra">Électrovanne de coupure de turbine</tu>
	<tu xmlns:lang="deu">Turbinenrad-Abschaltventil</tu>
	<tu xmlns:lang="ita">Valvola di arresto turbina</tu>
	<tu xmlns:lang="jpn">タービン シャットオフ バルブ</tu>
	<tu xmlns:lang="ptg">Válvula de corte da turbina</tu>
	<tu xmlns:lang="ptb">Válvula de corte da turbina</tu>
	<tu xmlns:lang="rus">клапан отсечки турбины</tu>
	<tu xmlns:lang="esp">Válvula de corte de la turbina</tu>
	<tu xmlns:lang="chs">涡轮切断阀</tu>
	<tu xmlns:lang="kor">터빈 차단 밸브</tu>
</tm>
