<?xml version="1.0" encoding="utf-8" ?>
<tm id="@J_14229_M_DESC_ATCM">
	<tu xmlns:lang="eng">All terrain control module</tu>
	<tu xmlns:lang="nld">Regelmodule van alle terreinen.</tu>
	<tu xmlns:lang="fra">Module de commande tout-terrain.</tu>
	<tu xmlns:lang="deu">Terrain-Response-Steuermodul.</tu>
	<tu xmlns:lang="ita">Modulo comando guida fuoristrada.</tu>
	<tu xmlns:lang="jpn">全範囲コントロール モジュール</tu>
	<tu xmlns:lang="ptg">Módulo de controlo das funções todo-o-terreno.</tu>
	<tu xmlns:lang="ptb">Módulo de controle All terrain</tu>
	<tu xmlns:lang="rus">Блок управления режимом повышенной проходимости.</tu>
	<tu xmlns:lang="esp">Módulo de control de todo-terreno.</tu>
	<tu xmlns:lang="chs">全部地形控制模块。</tu>
	<tu xmlns:lang="kor">전지형 컨트롤 모듈</tu>
</tm>
