<?xml version="1.0" encoding="utf-8" ?>
<tm id="@J_COUNTRY_SLOVENIA">
	<tu xmlns:lang="eng">Slovenia</tu>
	<tu xmlns:lang="nld">Slovenië</tu>
	<tu xmlns:lang="fra">Slovénie</tu>
	<tu xmlns:lang="deu">Slowenien</tu>
	<tu xmlns:lang="ita">Slovenia</tu>
	<tu xmlns:lang="jpn">スロベニア</tu>
	<tu xmlns:lang="ptg">Eslovénia</tu>
	<tu xmlns:lang="ptb">Eslovênia</tu>
	<tu xmlns:lang="rus">Словения</tu>
	<tu xmlns:lang="esp">Eslovenia</tu>
	<tu xmlns:lang="chs">斯洛文尼亚</tu>
	<tu xmlns:lang="kor">슬로베니아</tu>
</tm>
