<?xml version="1.0" encoding="utf-8" ?>
<tm id="@J_COUNTRY_INDONESIA">
	<tu xmlns:lang="eng">Indonesia</tu>
	<tu xmlns:lang="nld">Indonesië</tu>
	<tu xmlns:lang="fra">Indonésie</tu>
	<tu xmlns:lang="deu">Indonesien</tu>
	<tu xmlns:lang="ita">Indonesia</tu>
	<tu xmlns:lang="jpn">インドネシア</tu>
	<tu xmlns:lang="ptg">Indonésia</tu>
	<tu xmlns:lang="ptb">Indonésia</tu>
	<tu xmlns:lang="rus">Индонезия</tu>
	<tu xmlns:lang="esp">Indonesia</tu>
	<tu xmlns:lang="chs">印度尼西亚</tu>
	<tu xmlns:lang="kor">인도네시아</tu>
</tm>
