<?xml version="1.0" encoding="utf-8" ?>
<tm id="@J_I_DISP_IN_CTR_CONS">
	<tu xmlns:lang="eng">Display within the center console.</tu>
	<tu xmlns:lang="nld">Het display binnenin de middenconsole.</tu>
	<tu xmlns:lang="fra">Affichage sur la console centrale.</tu>
	<tu xmlns:lang="deu">Display in der Mittelkonsole.</tu>
	<tu xmlns:lang="ita">Display all'interno della consolle centrale.</tu>
	<tu xmlns:lang="jpn">センター コンソ\ール内のディスプレイ</tu>
	<tu xmlns:lang="ptg">Visor na consola central. </tu>
	<tu xmlns:lang="ptb">Visor dentro do console central.</tu>
	<tu xmlns:lang="rus">Дисплей в центральной консоли.</tu>
	<tu xmlns:lang="esp">Pantalla en la consola central.</tu>
	<tu xmlns:lang="chs">中央控制台内的显示器。</tu>
	<tu xmlns:lang="kor">센터 콘솔 내 디스플레이</tu>
</tm>
