<?xml version="1.0" encoding="utf-8" ?>
<tm id="@J_I_APPROX_10_MSECONDS">
	<tu xmlns:lang="eng">Approximately 10ms.</tu>
	<tu xmlns:lang="nld">Ongeveer 10 milliseconden.</tu>
	<tu xmlns:lang="fra">Environ 10 ms</tu>
	<tu xmlns:lang="deu">Ca. 10 ms.</tu>
	<tu xmlns:lang="ita">Circa 10 ms.</tu>
	<tu xmlns:lang="jpn">約 10ミリ秒</tu>
	<tu xmlns:lang="ptg">Aproximadamente 10 ms.</tu>
	<tu xmlns:lang="ptb">Aproximadamente 10 ms.</tu>
	<tu xmlns:lang="rus">Приблизительно 10 миллисекунд.</tu>
	<tu xmlns:lang="esp">10 ms, aproximadamente.</tu>
	<tu xmlns:lang="chs">约 10 毫秒。</tu>
	<tu xmlns:lang="kor">약 10ms</tu>
</tm>
