<?xml version="1.0" encoding="utf-8" ?>
<tm id="@J_I_180_MINS">
	<tu xmlns:lang="eng">180 minutes</tu>
	<tu xmlns:lang="nld">180 minuten</tu>
	<tu xmlns:lang="fra">180 minute</tu>
	<tu xmlns:lang="deu">180 Minuten</tu>
	<tu xmlns:lang="ita">180 minuti</tu>
	<tu xmlns:lang="jpn">180 分</tu>
	<tu xmlns:lang="ptg">180 minutos</tu>
	<tu xmlns:lang="ptb">180 minutos</tu>
	<tu xmlns:lang="rus">180 минут</tu>
	<tu xmlns:lang="esp">180 minutos</tu>
	<tu xmlns:lang="chs">180分钟</tu>
	<tu xmlns:lang="kor">180분</tu>
</tm>
