<?xml version="1.0" encoding="utf-8" ?>
<tm id="@J_I_LARGE_FUEL_PUMP">
	<tu xmlns:lang="eng">Large fuel pump for emergent markets</tu>
	<tu xmlns:lang="nld">Grote brandstofpomp voor opkomende markten</tu>
	<tu xmlns:lang="fra">Grande pompe à carburant pour marchés émergents</tu>
	<tu xmlns:lang="deu">Große Kraftstoffpumpe für aufstrebende Märkte</tu>
	<tu xmlns:lang="ita">Pompa carburante grande per mercati emergenti</tu>
	<tu xmlns:lang="jpn">新興市場向け大型フューエル ポンプ</tu>
	<tu
    xmlns:lang="ptg"
  >Bomba de combustível de grandes dimensões para mercados emergentes</tu>
	<tu xmlns:lang="ptb">Bomba de combustível grande para mercados emergentes</tu>
	<tu
    xmlns:lang="rus"
  >Топливный насос повышенной производительности для развивающихся рынков</tu>
	<tu xmlns:lang="esp">Bomba de combustible grande para mercados emergentes</tu>
	<tu xmlns:lang="chs">针对新兴市场的大型燃油泵</tu>
	<tu xmlns:lang="kor">신흥 시장용 대형 연료 펌프</tu>
</tm>
