<?xml version="1.0" encoding="utf-8" ?>
<tm id="@J_I_4_DOOR_SEDAN_6_STRETCH">
	<tu xmlns:lang="eng">4 door sedan stretch 6 </tu>
	<tu xmlns:lang="nld">4-deurs sedan stretch 6</tu>
	<tu xmlns:lang="fra">Berline 4 portes à empattement long 6</tu>
	<tu xmlns:lang="deu">4-türige Limousine 6, langer Radstand</tu>
	<tu xmlns:lang="ita">Berlina 4 porte lunga 6</tu>
	<tu xmlns:lang="jpn">4 ドア セダン ストレッチ 6</tu>
	<tu xmlns:lang="ptg">Sedan (Stretch) 6 de 4 portas</tu>
	<tu xmlns:lang="ptb">4 portas sedan estendido 6 </tu>
	<tu xmlns:lang="rus">4-дверный удлиненный седан 6</tu>
	<tu xmlns:lang="esp">Berlina ampliada de 4 puertas 6</tu>
	<tu xmlns:lang="chs">4 门轿车加长型 6</tu>
	<tu xmlns:lang="kor">4도어 세단 스트레치 6 </tu>
</tm>
