<?xml version="1.0" encoding="utf-8" ?>
<tm id="@J_I_5_SPD_MAN_TRANS">
	<tu xmlns:lang="eng">5 speed manual transmissions</tu>
	<tu xmlns:lang="nld">Handgeschakelde versnellingsbak met 5 versnellingen</tu>
	<tu xmlns:lang="fra">Transmissions manuelles 5 vitesses</tu>
	<tu xmlns:lang="deu">5-Gang-Schaltgetriebe</tu>
	<tu xmlns:lang="ita">Cambi manuali a 5 marce</tu>
	<tu xmlns:lang="jpn">5 速マニュアル トランスミッション</tu>
	<tu xmlns:lang="ptg">Transmissões manuais de 5 velocidades</tu>
	<tu xmlns:lang="ptb">Transmissões manuais de 5 velocidades</tu>
	<tu xmlns:lang="rus">5-скоростные механические коробки передач</tu>
	<tu xmlns:lang="esp">Cambios manuales de 5 velocidades</tu>
	<tu xmlns:lang="chs">5 速手动变速器</tu>
	<tu xmlns:lang="kor">5단 수동 변속기</tu>
</tm>
