<?xml version="1.0" encoding="utf-8" ?>
<tm id="@J_I_AUD_BUT_STEER">
	<tu xmlns:lang="eng">Audio buttons on steering wheel</tu>
	<tu xmlns:lang="nld">Audiotoetsen op stuurwiel</tu>
	<tu xmlns:lang="fra">Boutons audio au volant</tu>
	<tu xmlns:lang="deu">Audiotasten am Lenkrad</tu>
	<tu xmlns:lang="ita">Pulsanti audio su volante</tu>
	<tu xmlns:lang="jpn">ステアリング ホイールのオーディオ ボタン</tu>
	<tu xmlns:lang="ptg">Comandos áudio no volante</tu>
	<tu xmlns:lang="ptb">Botões de áudio no volante</tu>
	<tu xmlns:lang="rus">Кнопки управления аудиосистемой на рулевом колесе</tu>
	<tu xmlns:lang="esp">Mandos del sistema de audio en el volante</tu>
	<tu xmlns:lang="chs">方向盘上的音频按钮</tu>
	<tu xmlns:lang="kor">스티어링 휠의 오디오 버튼</tu>
</tm>
