<?xml version="1.0" encoding="utf-8" ?>
<tm id="@jboote2_1219831251$X">
	<tu xmlns:lang="eng">3.0L diesel V6 engine</tu>
	<tu xmlns:lang="nld">3.0L V6-dieselmotor</tu>
	<tu xmlns:lang="fra">Moteur V6 diesel 3.0L.</tu>
	<tu xmlns:lang="deu">3.0L V6-Dieselmotor</tu>
	<tu xmlns:lang="ita">Motore 3.0L diesel V6</tu>
	<tu xmlns:lang="jpn">3.0L ディーゼル V6 エンジン</tu>
	<tu xmlns:lang="ptg">Motor V6 3.0L Diesel</tu>
	<tu xmlns:lang="ptb">3,0 L, motor V6 a diesel</tu>
	<tu xmlns:lang="rus">Дизельный двигатель V6 3.0L</tu>
	<tu xmlns:lang="esp">Motor V6 Diesel 3.0L</tu>
	<tu xmlns:lang="chs">3.0L V6 柴油发动机</tu>
	<tu xmlns:lang="kor">3.0L 디젤 V6 엔진</tu>
</tm>
